{
  "repo_notes": [
    {
      "content": "请务必使用简体中文 (Simplified Chinese) 生成所有文档的内容、摘要和解释。我的目标受众是中国开发者。请注意：在生成文档时，请动态分析当前代码库的结构，适时更新新增的内容或添加新的章节目录。请侧重于解释系统的设计理念、模块职责、数据流向以及扩展方式。如果代码库中新增了模块或数据源，文档应能自动涵盖它们，而无需修改此指令。"
    }
  ],
  "pages": [
    {
      "title": "项目概览",
      "purpose": "介绍灾害预警插件的核心目标、主要功能特性以及整体架构设计理念。",
      "page_notes": [
        {
          "content": ""
        }
      ]
    },
    {
      "title": "快速开始",
      "purpose": "引导用户完成环境准备、插件安装、初始化配置以及首次运行。",
      "page_notes": [
        {
          "content": ""
        }
      ]
    },
    {
      "title": "安装指南",
      "purpose": "详细说明依赖项的安装步骤以及如何将插件集成到宿主机器人框架中。",
      "parent": "快速开始",
      "page_notes": [
        {
          "content": ""
        }
      ]
    },
    {
      "title": "配置指南",
      "purpose": "全面解析配置文件结构，包括数据源选择、过滤规则设定以及消息输出选项。",
      "parent": "快速开始",
      "page_notes": [
        {
          "content": ""
        }
      ]
    },
    {
      "title": "指令手册",
      "purpose": "自动扫描并列出所有用户可用的指令，说明其用途、参数格式及使用示例。",
      "parent": "快速开始",
      "page_notes": [
        {
          "content": ""
        }
      ]
    },
    {
      "title": "架构设计",
      "purpose": "阐述系统的整体架构分层以及各模块之间的协作关系。",
      "page_notes": [
        {
          "content": ""
        }
      ]
    },
    {
      "title": "系统全景",
      "purpose": "从宏观角度展示插件的逻辑分层（如数据层、处理层、表现层）及组件交互。",
      "parent": "架构设计",
      "page_notes": [
        {
          "content": ""
        }
      ]
    },
    {
      "title": "数据流转",
      "purpose": "详解数据从采集、解析、过滤、去重到最终推送的完整生命周期。",
      "parent": "架构设计",
      "page_notes": [
        {
          "content": ""
        }
      ]
    },
    {
      "title": "核心组件",
      "purpose": "分析系统中的关键服务模块、连接管理器及消息推送控制器的职责与实现。",
      "parent": "架构设计",
      "page_notes": [
        {
          "content": ""
        }
      ]
    },
    {
      "title": "数据源管理",
      "purpose": "概述目前支持的数据源类型及其集成方式。",
      "page_notes": [
        {
          "content": ""
        }
      ]
    },
    {
      "title": "支持的数据源列表",
      "purpose": "自动扫描并列出代码库中已实现的所有具体数据源，描述其覆盖区域及特性。",
      "parent": "数据源管理",
      "page_notes": [
        {
          "content": ""
        }
      ]
    },
    {
      "title": "连接与网络",
      "purpose": "说明网络连接的建立方式（如 WebSocket/HTTP）、心跳保活、自动重连及故障转移机制。",
      "parent": "数据源管理",
      "page_notes": [
        {
          "content": ""
        }
      ]
    },
    {
      "title": "数据处理器",
      "purpose": "文档化数据处理器的抽象设计，以及如何解析不同来源的原始数据格式。",
      "parent": "数据源管理",
      "page_notes": [
        {
          "content": ""
        }
      ]
    },
    {
      "title": "数据处理逻辑",
      "purpose": "解释灾害事件的统一建模、清洗、过滤及去重策略。",
      "page_notes": [
        {
          "content": ""
        }
      ]
    },
    {
      "title": "数据模型",
      "purpose": "文档化系统内部使用的通用数据结构（如地震、海啸、气象预警等对象的定义）。",
      "parent": "数据处理逻辑",
      "page_notes": [
        {
          "content": ""
        }
      ]
    },
    {
      "title": "事件过滤机制",
      "purpose": "解释过滤流水线的工作原理，包括基于阈值、区域或其他条件的筛选逻辑。",
      "parent": "数据处理逻辑",
      "page_notes": [
        {
          "content": ""
        }
      ]
    },
    {
      "title": "去重系统",
      "purpose": "说明如何识别跨数据源或短时间内的重复事件，防止消息轰炸。",
      "parent": "数据处理逻辑",
      "page_notes": [
        {
          "content": ""
        }
      ]
    },
    {
      "title": "消息系统",
      "purpose": "文档化预警消息的构建、渲染及多平台分发机制。",
      "page_notes": [
        {
          "content": ""
        }
      ]
    },
    {
      "title": "推送控制",
      "purpose": "解释消息推送的决策逻辑，包括发送频率控制及目标对象选择。",
      "parent": "消息系统",
      "page_notes": [
        {
          "content": ""
        }
      ]
    },
    {
      "title": "消息格式化",
      "purpose": "说明如何将内部数据模型转换为用户可读的文本或富媒体消息模板。",
      "parent": "消息系统",
      "page_notes": [
        {
          "content": ""
        }
      ]
    },
    {
      "title": "输出适配",
      "purpose": "解释如何根据不同平台特性适配消息展示，以及相关链接生成逻辑。",
      "parent": "消息系统",
      "page_notes": [
        {
          "content": ""
        }
      ]
    },
    {
      "title": "高级功能",
      "purpose": "涵盖除基础预警之外的扩展能力，如计算分析或地理辅助功能。",
      "page_notes": [
        {
          "content": ""
        }
      ]
    },
    {
      "title": "烈度计算算法",
      "purpose": "文档化用于估算本地影响程度的算法逻辑及所采用的标准。",
      "parent": "高级功能",
      "page_notes": [
        {
          "content": ""
        }
      ]
    },
    {
      "title": "本地化监测",
      "purpose": "说明如何基于用户位置进行个性化的预警分析和筛选。",
      "parent": "高级功能",
      "page_notes": [
        {
          "content": ""
        }
      ]
    },
    {
      "title": "地理信息处理",
      "purpose": "解释坐标到地名的反向解析或翻译机制。",
      "parent": "高级功能",
      "page_notes": [
        {
          "content": ""
        }
      ]
    },
    {
      "title": "日志与调试",
      "purpose": "说明系统的日志记录策略，以及用于排查问题的调试工具。",
      "parent": "高级功能",
      "page_notes": [
        {
          "content": ""
        }
      ]
    },
    {
      "title": "开发者指南",
      "purpose": "为希望修改或扩展本插件的开发者提供指导。",
      "page_notes": [
        {
          "content": ""
        }
      ]
    },
    {
      "title": "项目结构",
      "purpose": "解析代码库的文件组织方式及各模块的职责划分。",
      "parent": "开发者指南",
      "page_notes": [
        {
          "content": ""
        }
      ]
    },
    {
      "title": "扩展数据源",
      "purpose": "提供关于如何实现新数据源接口并注册到系统中的教程。",
      "parent": "开发者指南",
      "page_notes": [
        {
          "content": ""
        }
      ]
    },
    {
      "title": "测试与模拟",
      "purpose": "文档化内置的测试指令及模拟演练功能的使用方法。",
      "parent": "开发者指南",
      "page_notes": [
        {
          "content": ""
        }
      ]
    }
  ]
}
